odoo/addons/fs_folder_ms_drive/README.rst
odoo/addons/fs_folder_ms_drive/__init__.py
odoo/addons/fs_folder_ms_drive/__manifest__.py
odoo/addons/fs_folder_ms_drive/controllers/__init__.py
odoo/addons/fs_folder_ms_drive/controllers/fs_controller.py
odoo/addons/fs_folder_ms_drive/i18n/fs_folder_ms_drive.pot
odoo/addons/fs_folder_ms_drive/i18n/it.po
odoo/addons/fs_folder_ms_drive/models/__init__.py
odoo/addons/fs_folder_ms_drive/models/fs_folder_field_value_adapter.py
odoo/addons/fs_folder_ms_drive/models/fs_folder_field_web_api.py
odoo/addons/fs_folder_ms_drive/readme/CONFIGURE.md
odoo/addons/fs_folder_ms_drive/readme/CONTEXT.md
odoo/addons/fs_folder_ms_drive/readme/CONTRIBUTORS.md
odoo/addons/fs_folder_ms_drive/readme/CREDITS.md
odoo/addons/fs_folder_ms_drive/readme/DESCRIPTION.md
odoo/addons/fs_folder_ms_drive/static/description/icon.png
odoo/addons/fs_folder_ms_drive/static/description/index.html
odoo/addons/fs_folder_ms_drive/static/src/components/preview_iframe.esm.js
odoo/addons/fs_folder_ms_drive/static/src/components/preview_iframe.scss
odoo/addons/fs_folder_ms_drive/static/src/components/preview_iframe.xml
odoo/addons/fs_folder_ms_drive/static/src/fs_folder_ms_drive/fs_folder item.xml
odoo/addons/fs_folder_ms_drive/static/src/fs_folder_ms_drive/fs_folder.esm.js
odoo/addons/fs_folder_ms_drive/static/src/fs_folder_ms_drive/fs_folder.xml
odoo/addons/fs_folder_ms_drive/static/src/img/ms_drive_connected.png
odoo/addons/fs_folder_ms_drive/static/src/styles/ms-drive-icon.scss
odoo_addon_fs_folder_ms_drive-18.0.1.0.0.7.dist-info/METADATA
odoo_addon_fs_folder_ms_drive-18.0.1.0.0.7.dist-info/WHEEL
odoo_addon_fs_folder_ms_drive-18.0.1.0.0.7.dist-info/top_level.txt
odoo_addon_fs_folder_ms_drive-18.0.1.0.0.7.dist-info/RECORD
