Metadata-Version: 2.1
Name: odoo-addon-fs_folder_ms_drive
Version: 18.0.1.0.0.7
Requires-Python: >=3.10
Requires-Dist: odoo-addon-fs_folder==18.0.*
Requires-Dist: odoo-addon-fs_storage_ms_drive==18.0.*
Requires-Dist: odoo==18.0.*
Summary: Display and manage your files from Microsoft drives from within Odoo
Home-page: https://github.com/OCA/storage
License: LGPL-3
Author: ACSONE SA/NV,Odoo Community Association (OCA)
Author-email: support@odoo-community.org
Classifier: Programming Language :: Python
Classifier: Framework :: Odoo
Classifier: Framework :: Odoo :: 18.0
Classifier: License :: OSI Approved :: GNU Lesser General Public License v3 (LGPLv3)
